setup.py
a_gb_distributions/Binomialdistribution.py
a_gb_distributions/Gaussiandistribution.py
a_gb_distributions/Generaldistribution.py
a_gb_distributions/__init__.py
a_gb_distributions.egg-info/PKG-INFO
a_gb_distributions.egg-info/SOURCES.txt
a_gb_distributions.egg-info/dependency_links.txt
a_gb_distributions.egg-info/not-zip-safe
a_gb_distributions.egg-info/top_level.txt