Metadata-Version: 1.0
Name: a-gb-distributions
Version: 1.0
Summary: Gaussian and Binomial distributions
Home-page: UNKNOWN
Author: Ahmed Elshehawy
Author-email: UNKNOWN
License: UNKNOWN
Platform: UNKNOWN
